bioen/fileio.py
bioen/version.py
bioen/__init__.py
bioen/analyze/procedure.py
bioen/analyze/run_bioen.py
bioen/analyze/__init__.py
bioen/analyze/utils.py
bioen/analyze/show_plot/show_plot.py
bioen/analyze/show_plot/__init__.py
bioen/analyze/observables/observables.py
bioen/analyze/observables/__init__.py
bioen/analyze/observables/deer/deer.py
bioen/analyze/observables/deer/__init__.py
bioen/analyze/observables/scattering/scattering.py
bioen/analyze/observables/scattering/__init__.py
bioen/analyze/observables/generic/generic.py
bioen/analyze/observables/generic/__init__.py
bioen/analyze/observables/cd_data/cd_data.py
bioen/analyze/observables/cd_data/__init__.py
bioen/optimize/common.py
bioen/optimize/forces.py
bioen/optimize/util.py
bioen/optimize/log_weights.py
bioen/optimize/minimize.py
bioen/optimize/__init__.py
bioen/optimize/unused_code.py
bioen/optimize/ext/c_bioen_kernels_logw.h
bioen/optimize/ext/c_bioen_kernels_logw.c
bioen/optimize/ext/c_bioen_kernels_forces.c
bioen/optimize/ext/c_bioen_common.h
bioen/optimize/ext/c_bioen_kernels_forces.h
bioen/optimize/ext/c_bioen_error.c
bioen/optimize/ext/c_bioen.cpython-37m-x86_64-linux-gnu.so
bioen/optimize/ext/ompmagic.h
bioen/optimize/ext/c_bioen_common.c
bioen/optimize/ext/c_bioen.pyx
bioen/optimize/ext/_clang-format
bioen/optimize/ext/__init__.py
bioen/optimize/ext/c_bioen_error.h
bioen/optimize/config/bioen_optimize.yaml
bioen.libs/libgslcblas-49198ba0.so.0.0.0
bioen.libs/libgomp-a34b3233.so.1.0.0
bioen.libs/liblbfgs-1-06781254.10.so
bioen.libs/libgsl-db7eb9c6.so.23.1.0
bioen-0.1.3.dist-info/LICENSE.txt
bioen-0.1.3.dist-info/LICENSE-liblbfgs-1.10.txt
bioen-0.1.3.dist-info/METADATA
bioen-0.1.3.dist-info/WHEEL
bioen-0.1.3.dist-info/entry_points.txt
bioen-0.1.3.dist-info/LICENSE-gsl-2.5.txt
bioen-0.1.3.dist-info/top_level.txt
bioen-0.1.3.dist-info/LICENSE-libgomp.txt
bioen-0.1.3.dist-info/RECORD
