Metadata-Version: 2.1
Name: bioen
Version: 0.1.3
Summary: Bayesian Inference Of ENsembles
Author: Katrin Reichel, Juergen Koefinger, Cesar Allande, Klaus Reuter, Lukas S. Stelzl
Author-email: bioen@biophys.mpg.de
License-File: LICENSE-gsl-2.5.txt
License-File: LICENSE-libgomp.txt
License-File: LICENSE-liblbfgs-1.10.txt
License-File: LICENSE.txt
Requires-Dist: numpy
Requires-Dist: scipy
Requires-Dist: cython
Requires-Dist: pyyaml
Requires-Dist: pandas
Requires-Dist: h5py
Requires-Dist: MDAnalysis
Requires-Dist: pytest
